pyrage-1.3.0.dist-info/METADATA
pyrage-1.3.0.dist-info/WHEEL
pyrage-1.3.0.dist-info/licenses/LICENSE
pyrage/__init__.py
pyrage/pyrage.pyd
pyrage-1.3.0.dist-info/RECORD
