Metadata-Version: 2.4
Name: pyrage
Version: 1.3.0
Classifier: Programming Language :: Rust
Classifier: Operating System :: POSIX :: Linux
License-File: LICENSE
Summary: Python bindings for rage (age in Rust)
Home-Page: https://github.com/woodruffw/pyrage
Author: William Woodruff <william@yossarian.net>
Author-email: William Woodruff <william@yossarian.net>
License: MIT
Requires-Python: >=3.9
Project-URL: Source Code, https://github.com/woodruffw/pyrage
